{"id":"harvard-PSI","service_id":"2ff8540e-0959-40d3-85e7-9ddc59ca9dcb","plan_id":"3335b4f9-5f1e-4e5b-8c9b-7bde92621c5c","description":{"name":"Population Services International (PSI) Dataverse","type":"dataverse","url":"https://dataverse.harvard.edu/dataverse/PSI","identifier":"PSI","description":"PSI is a global health organization dedicated to improving the health of people in the developing world by focusing on serious challenges like a lack of family planning, HIV and AIDS, barriers to maternal health, and the greatest threats to children under five, including malaria, diarrhea, pneumonia and malnutrition. A hallmark of PSI is a commitment to the principle that health services and products are most effective when they are accompanied by robust communications and distribution efforts that help ensure wide acceptance and proper use. PSI works in partnership with local governments, ministries of health and local organizations to create health solutions that are built to last.","published_at":"2013-08-20T18:55:24Z","checksum":{"type":"","value":""}},"server_name":"harvard","server_url":"https://dataverse.harvard.edu","params":null}